sxmi_marker/ARUCO_DICT_7X7_1000.npz
sxmi_marker/__init__.py
sxmi_marker/cli.py
sxmi_marker/file_handler.py
sxmi_marker/identifier_handler.py
sxmi_marker/marker_generator.py
sxmi_marker/marker_workflow.py
sxmi_marker/py.typed
sxmi_marker-0.0.0.dist-info/METADATA
sxmi_marker-0.0.0.dist-info/WHEEL
sxmi_marker-0.0.0.dist-info/entry_points.txt
sxmi_marker-0.0.0.dist-info/RECORD
