Metadata-Version: 2.1
Name: sxmi-marker
Version: 0.0.0
Summary: Generates markers for SXMI modules
Home-page: https://github.com/Stroma-Vision/sxmi-marker
Author: Oguzhan Mete Ozturk
Author-email: metozturk@me.com
Requires-Python: >=3.10,<4.0
Classifier: Programming Language :: Python :: 3
Classifier: Programming Language :: Python :: 3.10
Classifier: Programming Language :: Python :: 3.11
Requires-Dist: numpy (>=1.25.2,<2.0.0)
Requires-Dist: typer[all] (==0.9.0)
Project-URL: Repository, https://github.com/Stroma-Vision/sxmi-marker
